compiler/__init__.py
compiler/__main__.py
compiler/code/powerStatus.code
compiler/code/bots/fillBotFactory.code
compiler/code/bots/fillRessource.code
compiler/code/bots/fillSpeedShield.code
compiler/code/bots/kamikase.code
compiler/code/bots/mineNearStore.code
compiler/code/bots/repare-BigBots.code
compiler/code/bots/repare-poly.code
compiler/code/bots/stopFreeBots.code
compiler/code/bots/unflagUnusedBots.code
compiler/code/bots/unloader.code
compiler/code/lib/idBots.code
compiler/code/lib/math.code
compiler/code/lib/msg.code
compiler/code/lib/onOff.code
compiler/code/lib/store.code
compiler/code/lib/time.code
compiler/lex/__init__.py
compiler/lex/keywords.py
compiler/lex/mainLex.py
compiler/yacc/__init__.py
compiler/yacc/generateYacc.py
compiler/yacc/mainYacc.py
compiler/yacc/p_functionYacc.py
compiler/yacc/parsetab.py
compiler/yacc/classes/AsmInst.py
compiler/yacc/classes/FunCall.py
compiler/yacc/classes/FunDef.py
compiler/yacc/classes/RefAndJump.py
compiler/yacc/classes/ValVarKey.py
compiler/yacc/classes/__init__.py
compiler/yacc/context/Context.py
compiler/yacc/context/__init__.py
compiler/yacc/grammar/__init__.py
compiler/yacc/grammar/_start.py
compiler/yacc/grammar/affectation.py
compiler/yacc/grammar/arguments.py
compiler/yacc/grammar/asm.py
compiler/yacc/grammar/asmError.py
compiler/yacc/grammar/dottedID.py
compiler/yacc/grammar/error.py
compiler/yacc/grammar/function.py
compiler/yacc/grammar/ifElseIf.py
compiler/yacc/grammar/imports.py
compiler/yacc/grammar/info.py
compiler/yacc/grammar/jump.py
compiler/yacc/grammar/lines.py
compiler/yacc/grammar/staticFor.py
compiler/yacc/grammar/InstrASM/IDxArgs.py
compiler/yacc/grammar/InstrASM/__init__.py
compiler/yacc/grammar/InstrASM/control.py
compiler/yacc/grammar/InstrASM/draw.py
compiler/yacc/grammar/InstrASM/op.py
compiler/yacc/grammar/InstrASM/radar.py
compiler/yacc/grammar/InstrASM/simple.py
compiler/yacc/grammar/InstrASM/ucontrol.py
compiler/yacc/grammar/InstrASM/ulocate.py
MindustryCompiler-2.1.dist-info/LICENSE
MindustryCompiler-2.1.dist-info/METADATA
MindustryCompiler-2.1.dist-info/WHEEL
MindustryCompiler-2.1.dist-info/entry_points.txt
MindustryCompiler-2.1.dist-info/top_level.txt
MindustryCompiler-2.1.dist-info/RECORD
