Metadata-Version: 2.1
Name: MindustryCompiler
Version: 2.1
Summary: language that compile to Mindusty ASM, jump instruction can use references instead of line number, and more ...
Home-page: https://github.com/Pythux/MindustryCompiler
Author: Pythux
License: ('GNU3',)
Platform: UNKNOWN
Classifier: Programming Language :: Python :: 3
Classifier: Operating System :: OS Independent
Classifier: Intended Audience :: Education
Classifier: License :: OSI Approved :: GNU General Public License v3 or later (GPLv3+)
Requires-Python: >=3.6
Requires-Dist: PyBoa
Requires-Dist: ply
